{
  "base_url": "https://api.pionex.com",
  "symbols": [
    "BTC.PERP_USDT",
    "ETH.PERP_USDT",
    "SOL.PERP_USDT",
    "BNB.PERP_USDT",
    "XRP.PERP_USDT",
    "DOGE.PERP_USDT",
    "ADA.PERP_USDT"
  ],
  "position_usdt": 50,
  "max_open_trades": 2,
  "breakout_change_percent": 0.35,
  "stop_loss_percent": 2.0,
  "take_profit_percent": 3.0,
  "check_interval_sec": 3,
  "cooldown_sec": 300,
  "idle_backoff_sec": 15,
  "dry_run": true,
  "log_csv": "logs/perp_trades.csv",
  "state_file": "logs/perp_state.json"
}

